ros_buildfarm/__init__.py
ros_buildfarm/argument.py
ros_buildfarm/binarydeb_job.py
ros_buildfarm/binaryrpm_job.py
ros_buildfarm/ci_job.py
ros_buildfarm/colcon.py
ros_buildfarm/common.py
ros_buildfarm/crumb_requester.py
ros_buildfarm/debian_repo.py
ros_buildfarm/devel_job.py
ros_buildfarm/doc_job.py
ros_buildfarm/git.py
ros_buildfarm/http_cache.py
ros_buildfarm/jenkins.py
ros_buildfarm/jenkins_credentials.py
ros_buildfarm/package_repo.py
ros_buildfarm/prerelease.py
ros_buildfarm/release_common.py
ros_buildfarm/release_job.py
ros_buildfarm/rosdoc_index.py
ros_buildfarm/rosdoc_lite.py
ros_buildfarm/rpm_repo.py
ros_buildfarm/sourcedeb_job.py
ros_buildfarm/sourcerpm_job.py
ros_buildfarm/status_page.py
ros_buildfarm/status_page_input.py
ros_buildfarm/trigger_job.py
ros_buildfarm/vcs.py
ros_buildfarm/workspace.py
ros_buildfarm/config/__init__.py
ros_buildfarm/config/build_file.py
ros_buildfarm/config/ci_build_file.py
ros_buildfarm/config/doc_build_file.py
ros_buildfarm/config/index.py
ros_buildfarm/config/loader.py
ros_buildfarm/config/plot_config.py
ros_buildfarm/config/release_build_file.py
ros_buildfarm/config/source_build_file.py
ros_buildfarm/scripts/__init__.py
ros_buildfarm/scripts/generate_all_jobs.py
ros_buildfarm/scripts/subprocess_reaper.py
ros_buildfarm/scripts/ci/__init__.py
ros_buildfarm/scripts/ci/build_task_generator.py
ros_buildfarm/scripts/ci/create_workspace.py
ros_buildfarm/scripts/ci/create_workspace_task_generator.py
ros_buildfarm/scripts/ci/generate_ci_job.py
ros_buildfarm/scripts/ci/generate_ci_jobs.py
ros_buildfarm/scripts/ci/generate_ci_maintenance_jobs.py
ros_buildfarm/scripts/ci/generate_ci_script.py
ros_buildfarm/scripts/ci/generate_install_lists.py
ros_buildfarm/scripts/ci/run_ci_job.py
ros_buildfarm/scripts/ci/run_ci_reconfigure_job.py
ros_buildfarm/scripts/devel/__init__.py
ros_buildfarm/scripts/devel/build_and_install.py
ros_buildfarm/scripts/devel/build_and_test.py
ros_buildfarm/scripts/devel/create_devel_task_generator.py
ros_buildfarm-4.1.0.dist-info/LICENSE
ros_buildfarm-4.1.0.dist-info/METADATA
ros_buildfarm-4.1.0.dist-info/WHEEL
ros_buildfarm-4.1.0.dist-info/top_level.txt
ros_buildfarm-4.1.0.dist-info/RECORD
