Metadata-Version: 2.1
Name: ros-buildfarm
Version: 4.1.0
Summary: Build farm used to build the ROS ecosystem's packages.
Home-page: https://github.com/ros-infrastructure/ros_buildfarm
Author: Dirk Thomas
Author-email: dthomas@osrfoundation.org
Maintainer: ROS Infrastructure Team
License: Apache 2.0
Project-URL: Source code, https://github.com/ros-infrastructure/ros_buildfarm
Project-URL: Issue tracker, https://github.com/ros-infrastructure/ros_buildfarm/issues
Keywords: ROS,buildfarm,catkin
Platform: UNKNOWN
Classifier: Programming Language :: Python
Classifier: License :: OSI Approved :: Apache Software License
Requires-Python: >=3.6
License-File: LICENSE
Requires-Dist: empy
Requires-Dist: PyYAML
Requires-Dist: catkin-pkg (>=0.2.6)
Requires-Dist: jenkinsapi
Requires-Dist: rosdistro (>=1.0.0)
Requires-Dist: vcstool (>=0.1.37)
Provides-Extra: test
Requires-Dist: flake8 (>=3.7) ; extra == 'test'
Requires-Dist: flake8-class-newline ; extra == 'test'
Requires-Dist: flake8-docstrings ; extra == 'test'
Requires-Dist: flake8-import-order ; extra == 'test'
Requires-Dist: pep8 ; extra == 'test'
Requires-Dist: pyflakes ; extra == 'test'
Requires-Dist: pytest ; extra == 'test'
